jinja_flowbite/__init__.py
jinja_flowbite/jinja_flowbite/__init__.py
jinja_flowbite/jinja_flowbite/controls/alert.jinja
jinja_flowbite/jinja_flowbite/controls/anchor.jinja
jinja_flowbite/jinja_flowbite/controls/badge.jinja
jinja_flowbite/jinja_flowbite/controls/button.jinja
jinja_flowbite/jinja_flowbite/controls/card.jinja
jinja_flowbite/jinja_flowbite/controls/checkbox.jinja
jinja_flowbite/jinja_flowbite/controls/dark_mode_toggle.jinja
jinja_flowbite/jinja_flowbite/controls/error_card.jinja
jinja_flowbite/jinja_flowbite/controls/help_tooltip.jinja
jinja_flowbite/jinja_flowbite/controls/input_label.jinja
jinja_flowbite/jinja_flowbite/controls/input_text.jinja
jinja_flowbite/jinja_flowbite/controls/radio.jinja
jinja_flowbite/jinja_flowbite/controls/range.jinja
jinja_flowbite/jinja_flowbite/controls/select.jinja
jinja_flowbite/jinja_flowbite/controls/spinner.jinja
jinja_flowbite/jinja_flowbite/controls/tab.jinja
jinja_flowbite/jinja_flowbite/controls/tab_anchor.jinja
jinja_flowbite/jinja_flowbite/controls/tab_content.jinja
jinja_flowbite/jinja_flowbite/controls/tab_control_anchor.jinja
jinja_flowbite/jinja_flowbite/controls/tab_control_body.jinja
jinja_flowbite/jinja_flowbite/controls/tab_control_header.jinja
jinja_flowbite/jinja_flowbite/controls/table.jinja
jinja_flowbite/jinja_flowbite/controls/table_static.jinja
jinja_flowbite/jinja_flowbite/controls/table_static_header_cell.jinja
jinja_flowbite/jinja_flowbite/controls/table_static_row.jinja
jinja_flowbite/jinja_flowbite/controls/table_static_row_cell.jinja
jinja_flowbite/jinja_flowbite/controls/toast.jinja
jinja_flowbite/jinja_flowbite/controls/toggle_switch.jinja
jinja_flowbite/jinja_flowbite/controls/tooltip.jinja
jinja_flowbite/jinja_flowbite/icons/adjustments_horizontal.jinja
jinja_flowbite/jinja_flowbite/icons/adjustments_vertical.jinja
jinja_flowbite/jinja_flowbite/icons/angle_down.jinja
jinja_flowbite/jinja_flowbite/icons/angle_left.jinja
jinja_flowbite/jinja_flowbite/icons/angle_right.jinja
jinja_flowbite-0.4.dev17.dist-info/LICENSE
jinja_flowbite-0.4.dev17.dist-info/METADATA
jinja_flowbite-0.4.dev17.dist-info/WHEEL
jinja_flowbite-0.4.dev17.dist-info/top_level.txt
jinja_flowbite-0.4.dev17.dist-info/RECORD
