Metadata-Version: 2.1
Name: jinja_flowbite
Version: 0.4.dev17
Summary: Flowbite-Based Jinja Components
Home-page: https://github.com/schaveyt/jinja-flowbite
Author: Todd Schavey
Author-email: schaveyt@gmail.com
License: MIT
Keywords: python flask jinja flowbite htmx
Platform: any
Requires-Python: >=3.9
License-File: LICENSE
Requires-Dist: setuptools ==69.5.1
Requires-Dist: wheel ==0.43.0
Requires-Dist: jinja2 ==3.1.4
Requires-Dist: twine
